[
  {
    "path": "19thBLMJoelbo-1.JPG",
    "alt": "alt"
  },
  {
    "path": "19thBLMJoelbo-3.JPG",
    "alt": "s"
  },
  {
    "path": "19thBLMJoelbo-4.JPG",
    "alt": "sd"
  },
  {
    "path": "19thBLMJoelbo-5.JPG",
    "alt": "asd"
  },
  {
    "path": "19thBLMJoelbo-6.JPG",
    "alt": ""
  },
  {
    "path": "19thBLMJoelbo-7.JPG",
    "alt": ""
  },
  {
    "path": "19thBLMJoelbo-10.JPG",
    "alt": ""
  },
  {
    "path": "19thBLMJoelbo-11.JPG",
    "alt": ""
  },
  {
    "path": "19thBLMJoelbo-12.JPG",
    "alt": ""
  },
  {
    "path": "19thBLMJoelbo-15.JPG",
    "alt": ""
  },
  {
    "path": "19thBLMJoelbo-16.JPG",
    "alt": ""
  },
  {
    "path": "19thBLMJoelbo-17.JPG",
    "alt": ""
  }
]
